gemseo_pymoo/__init__.py
gemseo_pymoo/algos/__init__.py
gemseo_pymoo/algos/stop_criteria.py
gemseo_pymoo/algos/opt/__init__.py
gemseo_pymoo/algos/opt/_base_pymoo_settings.py
gemseo_pymoo/algos/opt/_base_scaled_pymoo_algorithms_settings.py
gemseo_pymoo/algos/opt/pymoo.py
gemseo_pymoo/algos/opt/_settings/__init__.py
gemseo_pymoo/algos/opt/_settings/ga_settings.py
gemseo_pymoo/algos/opt/_settings/nsga2_settings.py
gemseo_pymoo/algos/opt/_settings/nsga3_settings.py
gemseo_pymoo/algos/opt/_settings/rnsga3_settings.py
gemseo_pymoo/algos/opt/_settings/unsga3_settings.py
gemseo_pymoo/algos/opt/core/__init__.py
gemseo_pymoo/algos/opt/core/pymoo_problem.py
gemseo_pymoo/post/__init__.py
gemseo_pymoo/post/base_pymoo_plot_post_settings.py
gemseo_pymoo/post/base_pymoo_post_settings.py
gemseo_pymoo/post/base_weighted_pymoo_post_algorithms_settings.py
gemseo_pymoo/post/compromise.py
gemseo_pymoo/post/compromise_settings.py
gemseo_pymoo/post/high_tradeoff.py
gemseo_pymoo/post/high_tradeoff_settings.py
gemseo_pymoo/post/petal.py
gemseo_pymoo/post/petal_settings.py
gemseo_pymoo/post/radar.py
gemseo_pymoo/post/radar_settings.py
gemseo_pymoo/post/scatter_pareto.py
gemseo_pymoo/post/scatter_pareto_settings.py
gemseo_pymoo/post/core/MultiObjectiveDiagram_options.json
gemseo_pymoo/post/core/__init__.py
gemseo_pymoo/post/core/decomposition_application.py
gemseo_pymoo/post/core/multi_objective_diagram.py
gemseo_pymoo/post/core/plot_features.py
gemseo_pymoo/problems/__init__.py
gemseo_pymoo/problems/analytical/__init__.py
gemseo_pymoo/problems/analytical/chankong_haimes.py
gemseo_pymoo/problems/analytical/knapsack.py
gemseo_pymoo/problems/analytical/viennet.py
gemseo_pymoo-5.0.0.dist-info/licenses/LICENSE.txt
gemseo_pymoo-5.0.0.dist-info/METADATA
gemseo_pymoo-5.0.0.dist-info/WHEEL
gemseo_pymoo-5.0.0.dist-info/entry_points.txt
gemseo_pymoo-5.0.0.dist-info/top_level.txt
gemseo_pymoo-5.0.0.dist-info/RECORD
